MANIFEST.in
README.txt
setup.py
beast2bpp/__init__.py
beast2bpp/beast2bpp.py
beast2bpp.egg-info/PKG-INFO
beast2bpp.egg-info/SOURCES.txt
beast2bpp.egg-info/dependency_links.txt
beast2bpp.egg-info/not-zip-safe
beast2bpp.egg-info/top_level.txt