Metadata-Version: 1.1
Name: beast2bpp
Version: 0.13
Summary: Script that converts starBeast xml format input files to BPP format
Home-page: https://github.com/brannala/Beast2BPP.git/package/beast2bpp
Author: Bruce Rannala
Author-email: brannala@ucdavis.edu
License: MIT
Platform: UNKNOWN
Classifier: Development Status :: 3 - Alpha
Classifier: License :: OSI Approved :: MIT License
Classifier: Programming Language :: Python :: 3.4
